sys_stats/__init__.py
sys_stats/app_server.py
sys_stats/sys_stats_cli.py
sys_stats/api/__init__.py
sys_stats/api/stats.py
sys_stats-0.1.0.dist-info/LICENSE
sys_stats-0.1.0.dist-info/METADATA
sys_stats-0.1.0.dist-info/WHEEL
sys_stats-0.1.0.dist-info/entry_points.txt
sys_stats-0.1.0.dist-info/top_level.txt
sys_stats-0.1.0.dist-info/RECORD
