Metadata-Version: 2.1
Name: sys-stats
Version: 0.1.0
Summary: An open-source Python tool to provide system stats over a web interface.
Home-page: UNKNOWN
Author: Amith Koujalgi
Author-email: koujalgi.amith@gmail.com
License: UNKNOWN
Platform: UNKNOWN
Classifier: Intended Audience :: Developers
Classifier: Operating System :: OS Independent
Classifier: Programming Language :: Python :: 3
Classifier: Programming Language :: Python :: 3.8
Requires-Dist: fastapi
Requires-Dist: fastapi-cors
Requires-Dist: uvicorn
Requires-Dist: requests
Requires-Dist: prettytable
Requires-Dist: PyYaml
Requires-Dist: pydantic
Requires-Dist: psutil
Requires-Dist: jinja2
Requires-Dist: humanfriendly
Requires-Dist: python-socketio
Requires-Dist: eventlet
Requires-Dist: httpx
Requires-Dist: pytest
Requires-Dist: pytest-html
Requires-Dist: pypandoc
